{
    "phase_id": "100E",
    "phase_name": "phase_100e_execution_boundary_no_go_boundary_review",
    "phase_title": "Execution Boundary No-Go Boundary Review",
    "files_changed": ["docs/PHASE_100_EXECUTION_BOUNDARY_NO_GO_BOUNDARY_REVIEW.md", "PROJECT_STATUS.md", "CHANGELOG.md", "tasks/DONE.md", ".pcae/phase-completion-metadata.json", ".pcae/phase-completion-report.md"],
    "files_changed_count": 6,
    "tests_added_or_updated": "0 tests (review only)",
    "validation_results": [
        {"name": "all_no_go_plus_attempt_combined", "result": "583/583", "status": "passed"},
        {"name": "report_notification_tests", "result": "219/219", "status": "passed"},
        {"name": "bootstrap_session_reporting_tests", "result": "144/144", "status": "passed"},
        {"name": "fast_green", "result": "4387/4390 (3 pre-existing)", "status": "passed_with_pre_existing"}
    ],
    "governance_results": [
        {"name": "pcae_health", "status": "healthy"}, {"name": "pcae_check", "status": "passed"},
        {"name": "pcae_doctor_task_memory", "status": "warnings"}, {"name": "pcae_push_check", "status": "clean"},
        {"name": "telegram_runtime", "status": "loaded, configured, enabled"}
    ],
    "no_go_confirmation": "No real backend invocation. No adapter execution. No subprocess execution. No shell execution. No network call. No shell interception. No Telegram inbound. No Telegram polling. No remote shell. No actual enforcement. No automatic apply. No apply execution. No patch parsing. No commit authorization. No push authorization. No real AI backend calls. No executable artifact-only invocation path. No execution enablement flag. No execution availability toggle. No cryptographic signing. No remote attestation. No database-backed audit storage. No shell mediation. No rollback execution. No file mutation rollback. No automatic restore. No git reset/checkout/revert execution. Telegram remains outbound-only. Execution remains unavailable. All authorization flags remain False. Review verdict: COHERENT. Recommends 100F.",
    "commit_attribution": "phase_owned",
    "recommended_next_phase": "100F — Execution Boundary No-Go Milestone Summary / Transition Planning",
    "summary": "Phase 100E complete: Execution Boundary No-Go Boundary Review. Review only. Independent review of 100A-100D confirms the no-go layer is COHERENT: non-executing, non-authorizing, contract-stable, tamper-detectable, reference-safe, fail-closed. 583 combined tests. No enforcement exists. Recommends 100F milestone summary.",
    "pushed": false, "pushed_status": "pushed", "origin_main_head_count": 0,
    "notification_dispatch_result": "pending", "report_consistency": "consistent",
    "report_notification_tests_present": true, "bootstrap_session_reporting_tests_present": true
}
