{
    "phase_id": "96D",
    "phase_name": "phase_96d_connected_demo",
    "phase_title": "Connected Execution-Adjacent Demo",
    "files_changed": [
        "src/pcae/commands/backend.py",
        "src/pcae/cli.py",
        "tests/test_backend_cli.py",
        "docs/PHASE_96_CONNECTED_EXECUTION_ADJACENT_PLAN_END_TO_END_DRY_RUN_DEMO.md",
        "PROJECT_STATUS.md",
        "CHANGELOG.md",
        "tasks/DONE.md",
        "tasks/active/20260630-1830-phase-96d-connected-demo.md"
    ],
    "files_changed_count": 8,
    "tests_added_or_updated": "6 tests_added",
    "validation_results": [
        {
            "name": "report_notification_tests",
            "result": "107/107",
            "status": "passed"
        },
        {
            "name": "bootstrap_session_reporting_tests",
            "result": "598/598",
            "status": "passed"
        },
        {
            "name": "fast_green",
            "result": "4142/4143 (1 pre-existing)",
            "status": "passed"
        },
        {
            "name": "backend_model_tests",
            "result": "703/703",
            "status": "passed"
        },
        {
            "name": "backend_cli_tests",
            "result": "255/256 (1 pre-existing)",
            "status": "passed"
        }
    ],
    "governance_results": [
        {
            "name": "pcae_health",
            "status": "healthy"
        },
        {
            "name": "pcae_check",
            "status": "passed"
        },
        {
            "name": "pcae_doctor_task_memory",
            "status": "warnings"
        },
        {
            "name": "pcae_push_check",
            "status": "clean (nothing_to_push)"
        },
        {
            "name": "telegram_runtime",
            "status": "loaded"
        }
    ],
    "no_go_confirmation": "No real backend invocation. No adapter execution. No subprocess execution. No network call. No shell interception. No Telegram inbound. No enforcement. No automatic apply. No apply execution. No commit/push authorization. No real AI backend calls. Next phase not started.",
    "phase_commits": [
        {
            "hash": "2b9ae44d",
            "subject": "Add connected demo"
        },
        {
            "hash": "6a2a4617",
            "subject": "Complete connected demo"
        }
    ],
    "commit_attribution": "phase_owned",
    "recommended_next_phase": "96E \u2014 Connected Automation Hardening",
    "summary": "Phase 96D complete: Connected Execution-Adjacent Demo. Full connected chain demo: runtime\u2192broker\u2192boundary\u2192bundle\u2192orchestration\u2192EA plan\u2192assessment. 6 tests. No execution. Recommends 96E.",
    "pushed": true,
    "pushed_status": "pushed",
    "origin_main_head_count": 0,
    "notification_dispatch_result": "queued",
    "report_consistency": "consistent"
}